FlaskVerifyCode/__init__.py
FlaskVerifyCode-1.0.3.dist-info/LICENSE
FlaskVerifyCode-1.0.3.dist-info/METADATA
FlaskVerifyCode-1.0.3.dist-info/WHEEL
FlaskVerifyCode-1.0.3.dist-info/top_level.txt
FlaskVerifyCode-1.0.3.dist-info/RECORD
